simpletorchvideo
