Metadata-Version: 2.1
Name: simpletorchvideo
Version: 0.2.7
Summary: Some useful video dataset in pytorch
Home-page: https://github.com/yindaheng98/simpletorchvideo
Author: yindaheng98
Author-email: yindaheng98@163.com
License: UNKNOWN
Platform: UNKNOWN
Classifier: Programming Language :: Python :: 3
Classifier: License :: OSI Approved :: MIT License
Classifier: Operating System :: OS Independent
License-File: LICENSE
